libttv2fast2furious.cpython-313-darwin.so
ttv2fast2furious/__init__.py
ttv2fast2furious/companion_limits.py
ttv2fast2furious/kepler.py
ttv2fast2furious/ttv2fast2furious.py
ttv2fast2furious/ttv_basis_functions.py
ttv2fast2furious-1.1.0.dist-info/METADATA
ttv2fast2furious-1.1.0.dist-info/WHEEL
ttv2fast2furious-1.1.0.dist-info/top_level.txt
ttv2fast2furious-1.1.0.dist-info/RECORD
