Metadata-Version: 2.2
Name: ttv2fast2furious
Version: 1.1.0
Summary: Open source tools for TTV analysis and parameter inference.
Home-page: http://github.com/shadden/TTV2Fast2Furious
Author: Sam Hadden
Author-email: shadden1107@gmail.com
License: GPL
Keywords: astronomy astrophysics
Classifier: Development Status :: 3 - Alpha
Classifier: Intended Audience :: Science/Research
Classifier: Intended Audience :: Developers
Classifier: Topic :: Software Development :: Build Tools
Classifier: Topic :: Scientific/Engineering :: Astronomy
Classifier: License :: OSI Approved :: GNU General Public License v3 or later (GPLv3+)
Classifier: Programming Language :: Python :: 2
Classifier: Programming Language :: Python :: 3
Requires-Dist: numpy
Requires-Dist: scipy
Requires-Dist: sympy
Requires-Dist: pandas
Dynamic: author
Dynamic: author-email
Dynamic: classifier
Dynamic: home-page
Dynamic: keywords
Dynamic: license
Dynamic: requires-dist
Dynamic: summary
